rtl/filelist.sv
`include "defines.sv"
`include "exp_lut.sv"
`include "exp_rtl.sv"

rtl/exp_lut.sv
module exp_lut (
    input  logic signed [`DATA_WIDTH-1:0] x_IntPart,    // Q16.16
    output logic signed [`DATA_WIDTH-1:0] exp_IntPart   // Q16.16
);

    localparam signed [`DATA_WIDTH-1:0] NEG_07 =  -7 <<< `FRAC_BITS;
    localparam signed [`DATA_WIDTH-1:0] NEG_06 =  -6 <<< `FRAC_BITS;
    localparam signed [`DATA_WIDTH-1:0] NEG_05 =  -5 <<< `FRAC_BITS;
    localparam signed [`DATA_WIDTH-1:0] NEG_04 =  -4 <<< `FRAC_BITS;
    localparam signed [`DATA_WIDTH-1:0] NEG_03 =  -3 <<< `FRAC_BITS;
    localparam signed [`DATA_WIDTH-1:0] NEG_02 =  -2 <<< `FRAC_BITS;
    localparam signed [`DATA_WIDTH-1:0] NEG_01 =  -1 <<< `FRAC_BITS;
    localparam signed [`DATA_WIDTH-1:0] POS_00 =   0 <<< `FRAC_BITS;
    localparam signed [`DATA_WIDTH-1:0] POS_01 =   1 <<< `FRAC_BITS;
    localparam signed [`DATA_WIDTH-1:0] POS_02 =   2 <<< `FRAC_BITS;
    localparam signed [`DATA_WIDTH-1:0] POS_03 =   3 <<< `FRAC_BITS;
    localparam signed [`DATA_WIDTH-1:0] POS_04 =   4 <<< `FRAC_BITS;
    localparam signed [`DATA_WIDTH-1:0] POS_05 =   5 <<< `FRAC_BITS;
    localparam signed [`DATA_WIDTH-1:0] POS_06 =   6 <<< `FRAC_BITS;
    localparam signed [`DATA_WIDTH-1:0] POS_07 =   7 <<< `FRAC_BITS;
    localparam signed [`DATA_WIDTH-1:0] POS_08 =   8 <<< `FRAC_BITS;
    localparam signed [`DATA_WIDTH-1:0] POS_09 =   9 <<< `FRAC_BITS;
    localparam signed [`DATA_WIDTH-1:0] POS_10 =  10 <<< `FRAC_BITS;

    always_comb begin
        case (x_IntPart)
            NEG_07 : exp_IntPart = 32'd60;          // exp( -7) = 0.000912
            NEG_06 : exp_IntPart = 32'd162;         // exp( -6) = 0.002479
            NEG_05 : exp_IntPart = 32'd442;         // exp( -5) = 0.006738
            NEG_04 : exp_IntPart = 32'd1200;        // exp( -4) = 0.018316
            NEG_03 : exp_IntPart = 32'd3263;        // exp( -3) = 0.049787
            NEG_02 : exp_IntPart = 32'd8869;        // exp( -2) = 0.135335
            NEG_01 : exp_IntPart = 32'd24109;       // exp( -1) = 0.367879
            POS_00 : exp_IntPart = 32'd65536;       // exp(  0) = 1.000000
            POS_01 : exp_IntPart = 32'd178145;      // exp(  1) = 2.718282
            POS_02 : exp_IntPart = 32'd484249;      // exp(  2) = 7.389056
            POS_03 : exp_IntPart = 32'd1316326;     // exp(  3) = 20.085537
            POS_04 : exp_IntPart = 32'd3578144;     // exp(  4) = 54.598150
            POS_05 : exp_IntPart = 32'd9726405;     // exp(  5) = 148.413159
            POS_06 : exp_IntPart = 32'd26439109;    // exp(  6) = 403.428793
            POS_07 : exp_IntPart = 32'd71868951;    // exp(  7) = 1096.633158
            POS_08 : exp_IntPart = 32'd195360063;   // exp(  8) = 2980.957987
            POS_09 : exp_IntPart = 32'd531043708;   // exp(  9) = 8103.083928
            POS_10 : exp_IntPart = 32'd1443526462;  // exp( 10) = 22026.465795
            default: exp_IntPart = '0;
        endcase
    end
endmodule

rtl/exp_rtl.sv
module exp_rtl #(
    parameter integer DATA_WIDTH = `DATA_WIDTH,
    parameter integer FRAC_BITS  = `FRAC_BITS
)(
    input  logic signed [DATA_WIDTH-1:0] x_IntFrac,
    input  logic                         clk,
    input  logic                         rst_n,
    output logic signed [DATA_WIDTH-1:0] exp_x
);

    // Slicing input x_IntFrac into integer and fraction parts
    // x_IntFrac    = x_IntPart_w + x_FracPart_w
    // x_IntPart_w  = { x_IntFrac [31:16], 16'd0 } 
    // x_FracPart_w =   x_IntFrac [15: 0]          Always positive [0,1)

    logic signed [DATA_WIDTH-1:0] x_IntPart_w;
    logic signed [DATA_WIDTH-1:0] x_FracPart_w;

    assign x_IntPart_w  = { x_IntFrac[DATA_WIDTH-1:FRAC_BITS],{FRAC_BITS{1'b0}} };
    assign x_FracPart_w = {1'b0, x_IntFrac[FRAC_BITS-1:0]};

    //------------------------------------------------------------------
    // Stage-1: exp(x_IntPart) from LUT and find polynomial coefficients
    //------------------------------------------------------------------

    logic signed [DATA_WIDTH-1:0] exp_IntPart_lut;

    exp_lut u_exp_lut (
        .x_IntPart   (x_IntPart_w),
        .exp_IntPart (exp_IntPart_lut)
    );

    // Chebyshev's Polynomial upto third order,
    // exp(t) = C0*T0(t) + C1*T1(t) + C2*T2(t) + C3*T3(t)
    // Here,
    //     T0(t) = 1
    //     T1(t) = t
    //     T2(t) = 2*t^2 - 1
    //     T3(t) = 4*t^3 - 3t
    // For Chebyshev on [-1,1], t = (2*x - 1) maps x in [0,1] to t in [-1,1]
    // Hence,
    // exp(t) = C0 + C1 * t + C2 * (2*t^2 -1) + C3 * (4*t^3 - 3*t)
    // Siimplifying and normalizing the coefficients,
    localparam signed [DATA_WIDTH-1:0] A0 = 32'sd65502;
    localparam signed [DATA_WIDTH-1:0] A1 = 32'sd66592;
    localparam signed [DATA_WIDTH-1:0] A2 = 32'sd27722;
    localparam signed [DATA_WIDTH-1:0] A3 = 32'sd18292;

    // exp(x) = A0 + A1 * x + A2 * x^2 + A3 * x^3
    // Estrin's Scheme,
    //        = (A0 + A1 * x) + x^2 ( A2 + A3 * x)

    logic signed [2*DATA_WIDTH-1:0] term0_s1;     // A0 + A1 *x
    logic signed [2*DATA_WIDTH-1:0] term1_s1;     // x*x
    logic signed [2*DATA_WIDTH-1:0] term2_s1;     // A2 + A3 * x
    logic signed [DATA_WIDTH-1:0] exp_IntPart_s1;

    always_ff @(posedge clk or negedge rst_n) begin
        if (!rst_n) begin
            term0_s1           <= '0;
            term1_s1           <= '0;
            term2_s1           <= '0;
            exp_IntPart_s1     <= '0;
        end
        else begin
            term0_s1 <= A0 + ((A1 * x_FracPart_w) >>> FRAC_BITS);     // A0 + A1 * x
            term1_s1 <= (x_FracPart_w * x_FracPart_w) >>> FRAC_BITS;  // x*x
            term2_s1 <= A2 + ((A3 * x_FracPart_w) >>> FRAC_BITS);     // A2 + A3 * x

            exp_IntPart_s1 <= exp_IntPart_lut;
        end
    end

    //------------------------------------------------------------------
    // Stage-2: exp_FracPart = term0_s1 + term1_s1 * term2_s1
    //------------------------------------------------------------------
    logic signed [DATA_WIDTH-1:0] exp_IntPart_s2;
    logic signed [DATA_WIDTH-1:0] exp_FracPart_s2;

    logic signed [2*DATA_WIDTH-1:0] term_1x2_s2;

    always_comb begin // term1_s1 * term2_s1
        term_1x2_s2 = (term1_s1 * term2_s1) >>> FRAC_BITS;
    end

    always_ff @(posedge clk or negedge rst_n) begin
        if (!rst_n) begin
            exp_IntPart_s2  <= '0;
            exp_FracPart_s2 <= '0;
        end
        else begin
            exp_IntPart_s2  <= exp_IntPart_s1;
            exp_FracPart_s2 <= term0_s1 + term_1x2_s2; // term0_s1 + term1_s1 * term2_s1
        end
    end

    //------------------------------------------------------------------
    // Stage-3 exp(x_IntFrac) = exp(x_IntPart) * exp(x_FracPart)
    //------------------------------------------------------------------
    logic signed [2*DATA_WIDTH - 1:0] product_w;

    assign product_w = (exp_IntPart_s2 * exp_FracPart_s2) >>> FRAC_BITS;

    always_ff @(posedge clk or negedge rst_n) begin
        if (!rst_n) begin
            exp_x <= '0;
        end
        else begin
            exp_x <= product_w;
        end
    end
endmodule

tb/tb_exp_rtl.sv
`timescale 1ns/1ps
`include "../rtl/filelist.sv"
module tb_exp_rtl;

    localparam DATA_WIDTH = `DATA_WIDTH;
    localparam FRAC_BITS  = `FRAC_BITS;
    localparam LATENCY    = 3;

    logic signed [DATA_WIDTH-1:0] x_IntFrac, exp_x;
    logic clk, rst_n;

    exp_rtl dut (.*);

    initial begin
        clk = 0;
        forever #5 clk = ~clk;
    end

    real x_q[$], exp_q[$];
    real worst_err;
    integer cycle_cnt;

    initial begin
        $dumpfile("output/exp_wave.vcd");
        $dumpvars(0, tb_exp_rtl);
    end

    // Reset
    initial begin
        rst_n = 0;
        x_IntFrac = 0;
        cycle_cnt = 0;
        worst_err = 0;
        repeat (5) @(posedge clk);
        rst_n = 1;
    end

    // Main Sequence
    initial begin
        wait (rst_n);
        $display("\n=========================================================================");
        $display("  x         Expected          Actual        %%Error");
        $display("=========================================================================");

        for (real x = -7.0; x <= 10.0; x += 0.1) begin
            real ref_val;
            x_IntFrac = $rtoi(x * (1 << FRAC_BITS));
            ref_val = ($exp(x) > 2147483647.0 / (1 << FRAC_BITS)) ?
                  2147483647.0 / (1 << FRAC_BITS) : $exp(x);
            x_q.push_back(x);
            exp_q.push_back(ref_val);
            @(posedge clk);
        end

        repeat (LATENCY + 4) @(posedge clk);
        $display("=========================================================================");
        $display("  Worst Error = %0.6f %%\n", worst_err);
        $finish;
    end

    // Scoreboard Check
    always @(posedge clk) begin
        if (rst_n) cycle_cnt <= cycle_cnt + 1;

        if (rst_n && cycle_cnt >= LATENCY && exp_q.size() > 0) begin
            real x_s, ref_s, act_s, err_s;
            x_s   = x_q.pop_front();
            ref_s = exp_q.pop_front();
            act_s = $itor(exp_x) / (1 << FRAC_BITS);
            err_s = (ref_s > 0) ? (100.0 * ((act_s > ref_s) ? act_s - ref_s : ref_s - act_s) / ref_s) : 0;
            if (err_s > worst_err) worst_err = err_s;
            $display("  %6.2f    %12.6f    %12.6f    %8.5f%%", x_s, ref_s, act_s, err_s);
        end
    end

endmodule

output/exp_wave.vcd
$version Generated by VerilatedVcd $end
$timescale 1ps $end
 $scope module TOP $end
  $scope module tb_exp_rtl $end
   $var wire 32 C DATA_WIDTH [31:0] $end
   $var wire 32 D FRAC_BITS [31:0] $end
   $var wire 32 E LATENCY [31:0] $end
   $var wire 32 0 x_IntFrac [31:0] $end
   $var wire 32 " exp_x [31:0] $end
   $var wire 1 1 clk $end
   $var wire 1 2 rst_n $end
   $var real 64 3 worst_err $end
   $var wire 32 5 cycle_cnt [31:0] $end
   $scope module dut $end
    $var wire 32 F DATA_WIDTH [31:0] $end
    $var wire 32 G FRAC_BITS [31:0] $end
    $var wire 32 0 x_IntFrac [31:0] $end
    $var wire 1 1 clk $end
    $var wire 1 2 rst_n $end
    $var wire 32 " exp_x [31:0] $end
    $var wire 32 6 x_IntPart_w [31:0] $end
    $var wire 32 7 x_FracPart_w [31:0] $end
    $var wire 32 8 exp_IntPart_lut [31:0] $end
    $var wire 32 H A0 [31:0] $end
    $var wire 32 I A1 [31:0] $end
    $var wire 32 J A2 [31:0] $end
    $var wire 32 K A3 [31:0] $end
    $var wire 64 # term0_s1 [63:0] $end
    $var wire 64 % term1_s1 [63:0] $end
    $var wire 64 ' term2_s1 [63:0] $end
    $var wire 32 ) exp_IntPart_s1 [31:0] $end
    $var wire 32 * exp_IntPart_s2 [31:0] $end
    $var wire 32 + exp_FracPart_s2 [31:0] $end
    $var wire 64 , term_1x2_s2 [63:0] $end
    $var wire 64 . product_w [63:0] $end
    $scope module u_exp_lut $end
     $var wire 32 6 x_IntPart [31:0] $end
     $var wire 32 8 exp_IntPart [31:0] $end
     $var wire 32 L NEG_07 [31:0] $end
     $var wire 32 M NEG_06 [31:0] $end
     $var wire 32 N NEG_05 [31:0] $end
     $var wire 32 O NEG_04 [31:0] $end
     $var wire 32 P NEG_03 [31:0] $end
     $var wire 32 Q NEG_02 [31:0] $end
     $var wire 32 R NEG_01 [31:0] $end
     $var wire 32 S POS_00 [31:0] $end
     $var wire 32 T POS_01 [31:0] $end
     $var wire 32 U POS_02 [31:0] $end
     $var wire 32 V POS_03 [31:0] $end
     $var wire 32 W POS_04 [31:0] $end
     $var wire 32 X POS_05 [31:0] $end
     $var wire 32 Y POS_06 [31:0] $end
     $var wire 32 Z POS_07 [31:0] $end
     $var wire 32 [ POS_08 [31:0] $end
     $var wire 32 \ POS_09 [31:0] $end
     $var wire 32 ] POS_10 [31:0] $end
    $upscope $end
   $upscope $end
   $scope module unnamedblk1 $end
    $scope module unnamedblk2 $end
     $var real 64 9 ref_val $end
    $upscope $end
   $upscope $end
   $scope module unnamedblk3 $end
    $var real 64 ; x_s $end
    $var real 64 = ref_s $end
    $var real 64 ? act_s $end
    $var real 64 A err_s $end
   $upscope $end
  $upscope $end
 $upscope $end
$enddefinitions $end


#0
b00000000000000000000000000000000 "
b0000000000000000000000000000000000000000000000000000000000000000 #
b0000000000000000000000000000000000000000000000000000000000000000 %
b0000000000000000000000000000000000000000000000000000000000000000 '
b00000000000000000000000000000000 )
b00000000000000000000000000000000 *
b00000000000000000000000000000000 +
b0000000000000000000000000000000000000000000000000000000000000000 ,
b0000000000000000000000000000000000000000000000000000000000000000 .
b00000000000000000000000000000000 0
01
02
r0 3
b00000000000000000000000000000000 5
b00000000000000000000000000000000 6
b00000000000000000000000000000000 7
b00000000000000010000000000000000 8
r0 9
r0 ;
r0 =
r0 ?
r0 A
b00000000000000000000000000100000 C
b00000000000000000000000000010000 D
b00000000000000000000000000000011 E
b00000000000000000000000000100000 F
b00000000000000000000000000010000 G
b00000000000000001111111111011110 H
b00000000000000010000010000100000 I
b00000000000000000110110001001010 J
b00000000000000000100011101110100 K
b11111111111110010000000000000000 L
b11111111111110100000000000000000 M
b11111111111110110000000000000000 N
b11111111111111000000000000000000 O
b11111111111111010000000000000000 P
b11111111111111100000000000000000 Q
b11111111111111110000000000000000 R
b00000000000000000000000000000000 S
b00000000000000010000000000000000 T
b00000000000000100000000000000000 U
b00000000000000110000000000000000 V
b00000000000001000000000000000000 W
b00000000000001010000000000000000 X
b00000000000001100000000000000000 Y
b00000000000001110000000000000000 Z
b00000000000010000000000000000000 [
b00000000000010010000000000000000 \
b00000000000010100000000000000000 ]
#1825000
#10000
01
#15000
11
#20000
01
#25000
11
#30000
01
#35000
11
#40000
01
#45000
b0000000000000000000000000000000000000000000000001111111111011110 #
b0000000000000000000000000000000000000000000000000110110001001010 '
b00000000000000000000000000111100 )
b11111111111110010000000000000000 0
11
12
b00000000000000000000000000000001 5
b11111111111110010000000000000000 6
b00000000000000000000000000111100 8
r0.0009118819655545162 9
#50000
01
#55000
b0000000000000000000000000000000000000000000000010001100111100001 #
b0000000000000000000000000000000000000000000000000000001010001111 %
b0000000000000000000000000000000000000000000000000111001101101111 '
b00000000000000000000000000111100 *
b00000000000000001111111111011110 +
b0000000000000000000000000000000000000000000000000000000100100111 ,
b0000000000000000000000000000000000000000000000000000000000111011 .
b11111111111110010001100110011010 0
11
b00000000000000000000000000000010 5
b00000000000000000001100110011010 7
r0.00100778542904851 9
#60000
01
#65000
b00000000000000000000000000111011 "
b0000000000000000000000000000000000000000000000010011001111100101 #
b0000000000000000000000000000000000000000000000000000101000111101 %
b0000000000000000000000000000000000000000000000000111101010010100 '
b00000000000000010001101100001000 +
b0000000000000000000000000000000000000000000000000000010011100110 ,
b0000000000000000000000000000000000000000000000000000000001000010 .
b11111111111110010011001100110100 0
11
b00000000000000000000000000000011 5
b00000000000000000011001100110100 7
r0.001113775147844802 9
#70000
01
#75000
b00000000000000000000000001000010 "
b0000000000000000000000000000000000000000000000010100110111100111 #
b0000000000000000000000000000000000000000000000000001011100001010 %
b0000000000000000000000000000000000000000000000001000000110111001 '
b00000000000000010011100011001011 +
b0000000000000000000000000000000000000000000000000000101110101100 ,
b0000000000000000000000000000000000000000000000000000000001001001 .
b11111111111110010100110011001101 0
11
r1.273565143922341 3
b00000000000000000000000000000100 5
b00000000000000000100110011001101 7
r0.00123091190267348 9
r-7 ;
r0.0009118819655545162 =
r0.0009002685546875 ?
r1.273565143922341 A
#80000
01
#85000
b00000000000000000000000001001001 "
b0000000000000000000000000000000000000000000000010110011111101011 #
b0000000000000000000000000000000000000000000000000010100011110110 %
b0000000000000000000000000000000000000000000000001000100011011110 '
b00000000000000010101100110010011 +
b0000000000000000000000000000000000000000000000000001010111100110 ,
b0000000000000000000000000000000000000000000000000000000001010000 .
b11111111111110010110011001100111 0
11
b00000000000000000000000000000101 5
b00000000000000000110011001100111 7
r0.001360368037547891 9
r-6.9 ;
r0.00100778542904851 =
r0.001007080078125 ?
r0.0699901887028077 A
#90000
01
#95000
b00000000000000000000000001010000 "
b0000000000000000000000000000000000000000000000011000000111101110 #
b0000000000000000000000000000000000000000000000000100000000000000 %
b0000000000000000000000000000000000000000000000001001000000000100 '
b00000000000000010111110111010001 +
b0000000000000000000000000000000000000000000000000010010000000001 ,
b0000000000000000000000000000000000000000000000000000000001011001 .
b11111111111110011000000000000000 0
11
b00000000000000000000000000000110 5
b00000000000000001000000000000000 7
r0.00150343919297757 9
r-6.800000000000001 ;
r0.001113775147844802 =
r0.0011138916015625 ?
r0.01045576550374297 A
#100000
01
#105000
b00000000000000000000000001011001 "
b0000000000000000000000000000000000000000000000011001101111110001 #
b0000000000000000000000000000000000000000000000000101110000101001 %
b0000000000000000000000000000000000000000000000001001011100101001 '
b00000000000000011010010111101111 +
b0000000000000000000000000000000000000000000000000011011001101010 ,
b0000000000000000000000000000000000000000000000000000000001100010 .
b11111111111110011001100110011010 0
11
b00000000000000000000000000000111 5
b00000000000000001001100110011010 7
r0.001661557273173931 9
r-6.700000000000001 ;
r0.00123091190267348 =
r0.001220703125 ?
r0.829367044977545 A
#110000
01
#115000
b00000000000000000000000001100010 "
b0000000000000000000000000000000000000000000000011011010111110101 #
b0000000000000000000000000000000000000000000000000111110101110001 %
b0000000000000000000000000000000000000000000000001001111001001110 '
b00000000000000011101001001011011 +
b0000000000000000000000000000000000000000000000000100110110010001 ,
b0000000000000000000000000000000000000000000000000000000001101101 .
b11111111111110011011001100110100 0
11
b00000000000000000000000000001000 5
b00000000000000001011001100110100 7
r0.001836304777028902 9
r-6.600000000000001 ;
r0.001360368037547891 =
r0.0013580322265625 ?
r0.1717043418339834 A
#120000
01
#125000
b00000000000000000000000001101101 "
b0000000000000000000000000000000000000000000000011100111111110111 #
b0000000000000000000000000000000000000000000000001010001111010111 %
b0000000000000000000000000000000000000000000000001010010101110011 '
b00000000000000100000001110000110 +
b0000000000000000000000000000000000000000000000000110100111100011 ,
b0000000000000000000000000000000000000000000000000000000001111000 .
b11111111111110011100110011001101 0
11
b00000000000000000000000000001001 5
b00000000000000001100110011001101 7
r0.002029430636295728 9
r-6.500000000000002 ;
r0.00150343919297757 =
r0.001495361328125 ?
r0.5372924219549916 A
#130000
01
#135000
b00000000000000000000000001111000 "
b0000000000000000000000000000000000000000000000011110100111111011 #
b0000000000000000000000000000000000000000000000001100111101011101 %
b0000000000000000000000000000000000000000000000001010110010011000 '
b00000000000000100011100111011010 +
b0000000000000000000000000000000000000000000000001000101111001101 ,
b0000000000000000000000000000000000000000000000000000000010000101 .
b11111111111110011110011001100111 0
11
b00000000000000000000000000001010 5
b00000000000000001110011001100111 7
r0.002242867719485795 9
r-6.400000000000002 ;
r0.001661557273173931 =
r0.0016632080078125 ?
r0.09934864510663921 A
#140000
01
#145000
b00000000000000000000000010000101 "
b0000000000000000000000000000000000000000000000001111111111011110 #
b0000000000000000000000000000000000000000000000000000000000000000 %
b0000000000000000000000000000000000000000000000000110110001001010 '
b00000000000000000000000010100010 )
b00000000000000100111010111001000 +
b0000000000000000000000000000000000000000000000000000000000000000 ,
b0000000000000000000000000000000000000000000000000000000010010011 .
b11111111111110100000000000000000 0
11
b00000000000000000000000000001011 5
b11111111111110100000000000000000 6
b00000000000000000000000000000000 7
b00000000000000000000000010100010 8
r0.00247875217666635 9
r-6.300000000000002 ;
r0.001836304777028902 =
r0.0018310546875 ?
r0.2859051283086499 A
#150000
01
#155000
b00000000000000000000000010010011 "
b0000000000000000000000000000000000000000000000010001100111100001 #
b0000000000000000000000000000000000000000000000000000001010001111 %
b0000000000000000000000000000000000000000000000000111001101101111 '
b00000000000000000000000010100010 *
b00000000000000001111111111011110 +
b0000000000000000000000000000000000000000000000000000000100100111 ,
b0000000000000000000000000000000000000000000000000000000010100001 .
b11111111111110100001100110011010 0
11
b00000000000000000000000000001100 5
b00000000000000000001100110011010 7
r0.002739444818768358 9
r-6.200000000000003 ;
r0.002029430636295728 =
r0.0020294189453125 ?
r0.0005760720775222764 A
#160000
01
#165000
b00000000000000000000000010100001 "
b0000000000000000000000000000000000000000000000010011001111100101 #
b0000000000000000000000000000000000000000000000000000101000111101 %
b0000000000000000000000000000000000000000000000000111101010010100 '
b00000000000000010001101100001000 +
b0000000000000000000000000000000000000000000000000000010011100110 ,
b0000000000000000000000000000000000000000000000000000000010110011 .
b11111111111110100011001100110100 0
11
b00000000000000000000000000001101 5
b00000000000000000011001100110100 7
r0.003027554745375802 9
r-6.100000000000003 ;
r0.002242867719485795 =
r0.0022430419921875 ?
r0.007770083816839738 A
#170000
01
#175000
b00000000000000000000000010110011 "
b0000000000000000000000000000000000000000000000010100110111100111 #
b0000000000000000000000000000000000000000000000000001011100001010 %
b0000000000000000000000000000000000000000000000001000000110111001 '
b00000000000000010011100011001011 +
b0000000000000000000000000000000000000000000000000000101110101100 ,
b0000000000000000000000000000000000000000000000000000000011000101 .
b11111111111110100100110011001101 0
11
b00000000000000000000000000001110 5
b00000000000000000100110011001101 7
r0.003345965457471257 9
r-6.000000000000004 ;
r0.00247875217666635 =
r0.0024566650390625 ?
r0.8910587275229184 A
#180000
01
#185000
b00000000000000000000000011000101 "
b0000000000000000000000000000000000000000000000010110011111101011 #
b0000000000000000000000000000000000000000000000000010100011110110 %
b0000000000000000000000000000000000000000000000001000100011011110 '
b00000000000000010101100110010011 +
b0000000000000000000000000000000000000000000000000001010111100110 ,
b0000000000000000000000000000000000000000000000000000000011011010 .
b11111111111110100110011001100111 0
11
b00000000000000000000000000001111 5
b00000000000000000110011001100111 7
r0.003697863716482913 9
r-5.900000000000004 ;
r0.002739444818768358 =
r0.0027313232421875 ?
r0.2964679750150917 A
#190000
01
#195000
b00000000000000000000000011011010 "
b0000000000000000000000000000000000000000000000011000000111101110 #
b0000000000000000000000000000000000000000000000000100000000000000 %
b0000000000000000000000000000000000000000000000001001000000000100 '
b00000000000000010111110111010001 +
b0000000000000000000000000000000000000000000000000010010000000001 ,
b0000000000000000000000000000000000000000000000000000000011110001 .
b11111111111110101000000000000000 0
11
b00000000000000000000000000010000 5
b00000000000000001000000000000000 7
r0.004086771438464045 9
r-5.800000000000004 ;
r0.003027554745375802 =
r0.0030059814453125 ?
r0.712565151670744 A
#200000
01
#205000
b00000000000000000000000011110001 "
b0000000000000000000000000000000000000000000000011001101111110001 #
b0000000000000000000000000000000000000000000000000101110000101001 %
b0000000000000000000000000000000000000000000000001001011100101001 '
b00000000000000011010010111101111 +
b0000000000000000000000000000000000000000000000000011011001101010 ,
b0000000000000000000000000000000000000000000000000000000100001011 .
b11111111111110101001100110011010 0
11
b00000000000000000000000000010001 5
b00000000000000001001100110011010 7
r0.004516580942612643 9
r-5.700000000000005 ;
r0.003345965457471257 =
r0.003326416015625 ?
r0.5842690874947628 A
#210000
01
#215000
b00000000000000000000000100001011 "
b0000000000000000000000000000000000000000000000011011010111110101 #
b0000000000000000000000000000000000000000000000000111110101110001 %
b0000000000000000000000000000000000000000000000001001111001001110 '
b00000000000000011101001001011011 +
b0000000000000000000000000000000000000000000000000100110110010001 ,
b0000000000000000000000000000000000000000000000000000000100100111 .
b11111111111110101011001100110100 0
11
b00000000000000000000000000010010 5
b00000000000000001011001100110100 7
r0.004991593906910186 9
r-5.600000000000005 ;
r0.003697863716482913 =
r0.0036773681640625 ?
r0.5542538609266571 A
#220000
01
#225000
b00000000000000000000000100100111 "
b0000000000000000000000000000000000000000000000011100111111110111 #
b0000000000000000000000000000000000000000000000001010001111010111 %
b0000000000000000000000000000000000000000000000001010010101110011 '
b00000000000000100000001110000110 +
b0000000000000000000000000000000000000000000000000110100111100011 ,
b0000000000000000000000000000000000000000000000000000000101000110 .
b11111111111110101100110011001101 0
11
b00000000000000000000000000010011 5
b00000000000000001100110011001101 7
r0.005516564420760737 9
r-5.500000000000005 ;
r0.004086771438464045 =
r0.0040740966796875 ?
r0.3101411216015678 A
#230000
01
#235000
b00000000000000000000000101000110 "
b0000000000000000000000000000000000000000000000011110100111111011 #
b0000000000000000000000000000000000000000000000001100111101011101 %
b0000000000000000000000000000000000000000000000001010110010011000 '
b00000000000000100011100111011010 +
b0000000000000000000000000000000000000000000000001000101111001101 ,
b0000000000000000000000000000000000000000000000000000000101101000 .
b11111111111110101110011001100111 0
11
b00000000000000000000000000010100 5
b00000000000000001110011001100111 7
r0.006096746565515595 9
r-5.400000000000006 ;
r0.004516580942612643 =
r0.0045013427734375 ?
r0.337382842658144 A
#240000
01
#245000
b00000000000000000000000101101000 "
b0000000000000000000000000000000000000000000000001111111111011110 #
b0000000000000000000000000000000000000000000000000000000000000000 %
b0000000000000000000000000000000000000000000000000110110001001010 '
b00000000000000000000000110111010 )
b00000000000000100111010111001000 +
b0000000000000000000000000000000000000000000000000000000000000000 ,
b0000000000000000000000000000000000000000000000000000000110001110 .
b11111111111110110000000000000000 0
11
b00000000000000000000000000010101 5
b11111111111110110000000000000000 6
b00000000000000000000000000000000 7
b00000000000000000000000110111010 8
r0.006737946999085419 9
r-5.300000000000006 ;
r0.004991593906910186 =
r0.004974365234375 ?
r0.3451537295799438 A
#250000
01
#255000
b00000000000000000000000110001110 "
b0000000000000000000000000000000000000000000000010001100111100001 #
b0000000000000000000000000000000000000000000000000000001010001111 %
b0000000000000000000000000000000000000000000000000111001101101111 '
b00000000000000000000000110111010 *
b00000000000000001111111111011110 +
b0000000000000000000000000000000000000000000000000000000100100111 ,
b0000000000000000000000000000000000000000000000000000000110111001 .
b11111111111110110001100110011010 0
11
b00000000000000000000000000010110 5
b00000000000000000001100110011010 7
r0.007446583070924285 9
r-5.200000000000006 ;
r0.005516564420760737 =
r0.0054931640625 ?
r0.4241835402605511 A
#260000
01
#265000
b00000000000000000000000110111001 "
b0000000000000000000000000000000000000000000000010011001111100101 #
b0000000000000000000000000000000000000000000000000000101000111101 %
b0000000000000000000000000000000000000000000000000111101010010100 '
b00000000000000010001101100001000 +
b0000000000000000000000000000000000000000000000000000010011100110 ,
b0000000000000000000000000000000000000000000000000000000111101000 .
b11111111111110110011001100110100 0
11
b00000000000000000000000000010111 5
b00000000000000000011001100110100 7
r0.008229747049019964 9
r-5.100000000000007 ;
r0.006096746565515595 =
r0.006072998046875 ?
r0.3895277322977612 A
#270000
01
#275000
b00000000000000000000000111101000 "
b0000000000000000000000000000000000000000000000010100110111100111 #
b0000000000000000000000000000000000000000000000000001011100001010 %
b0000000000000000000000000000000000000000000000001000000110111001 '
b00000000000000010011100011001011 +
b0000000000000000000000000000000000000000000000000000101110101100 ,
b0000000000000000000000000000000000000000000000000000001000011100 .
b11111111111110110100110011001101 0
11
b00000000000000000000000000011000 5
b00000000000000000100110011001101 7
r0.009095277101695743 9
r-5.000000000000007 ;
r0.006737946999085419 =
r0.0067291259765625 ?
r0.1309155819141442 A
#280000
01
#285000
b00000000000000000000001000011100 "
b0000000000000000000000000000000000000000000000010110011111101011 #
b0000000000000000000000000000000000000000000000000010100011110110 %
b0000000000000000000000000000000000000000000000001000100011011110 '
b00000000000000010101100110010011 +
b0000000000000000000000000000000000000000000000000001010111100110 ,
b0000000000000000000000000000000000000000000000000000001001010100 .
b11111111111110110110011001100111 0
11
b00000000000000000000000000011001 5
b00000000000000000110011001100111 7
r0.0100518357446335 9
r-4.900000000000007 ;
r0.007446583070924285 =
r0.0074462890625 ?
r0.003948232652277704 A
#290000
01
#295000
b00000000000000000000001001010100 "
b0000000000000000000000000000000000000000000000011000000111101110 #
b0000000000000000000000000000000000000000000000000100000000000000 %
b0000000000000000000000000000000000000000000000001001000000000100 '
b00000000000000010111110111010001 +
b0000000000000000000000000000000000000000000000000010010000000001 ,
b0000000000000000000000000000000000000000000000000000001010010011 .
b11111111111110111000000000000000 0
11
b00000000000000000000000000011010 5
b00000000000000001000000000000000 7
r0.01110899653824221 9
r-4.800000000000008 ;
r0.008229747049019964 =
r0.00823974609375 ?
r0.1214988099935161 A
#300000
01
#305000
b00000000000000000000001010010011 "
b0000000000000000000000000000000000000000000000011001101111110001 #
b0000000000000000000000000000000000000000000000000101110000101001 %
b0000000000000000000000000000000000000000000000001001011100101001 '
b00000000000000011010010111101111 +
b0000000000000000000000000000000000000000000000000011011001101010 ,
b0000000000000000000000000000000000000000000000000000001011011000 .
b11111111111110111001100110011010 0
11
b00000000000000000000000000011011 5
b00000000000000001001100110011010 7
r0.01227733990306833 9
r-4.700000000000008 ;
r0.009095277101695743 =
r0.00909423828125 ?
r0.01142153706948626 A
#310000
01
#315000
b00000000000000000000001011011000 "
b0000000000000000000000000000000000000000000000011011010111110101 #
b0000000000000000000000000000000000000000000000000111110101110001 %
b0000000000000000000000000000000000000000000000001001111001001110 '
b00000000000000011101001001011011 +
b0000000000000000000000000000000000000000000000000100110110010001 ,
b0000000000000000000000000000000000000000000000000000001100100101 .
b11111111111110111011001100110100 0
11
b00000000000000000000000000011100 5
b00000000000000001011001100110100 7
r0.0135685590122008 9
r-4.600000000000009 ;
r0.0100518357446335 =
r0.0100555419921875 ?
r0.03687135015097048 A
#320000
01
